kpihx_todo/__init__.py
kpihx_todo/cli.py
kpihx_todo-0.4.0.dist-info/WHEEL
kpihx_todo-0.4.0.dist-info/entry_points.txt
kpihx_todo-0.4.0.dist-info/METADATA
kpihx_todo-0.4.0.dist-info/RECORD
