Metadata-Version: 2.3
Name: kpihx-todo
Version: 0.4.0
Summary: A modern and productive CLI for managing your daily tasks.
Author: Ivann KAMDEM
Author-email: Ivann KAMDEM <kapoivha@gmail.com>
License: MIT
Requires-Dist: typer>=0.20.1
Requires-Python: >=3.8
